{
  "best_val_score": 0.6,
  "test": {
    "clip_acc": 0.45,
    "clip_f1": 0.56,
    "clip_auc": 0.5371428571428571,
    "video_acc": 0.4166666666666667,
    "video_f1": 0.36363636363636365,
    "video_auc": 0.37142857142857144
  },
  "history": [
    {
      "epoch": 1,
      "train_loss": 0.08331372228360945,
      "clip_acc": 0.32727272727272727,
      "clip_f1": 0.2127659574468085,
      "clip_auc": 0.7344322344322344,
      "video_acc": 0.6153846153846154,
      "video_f1": 0.6153846153846154,
      "video_auc": 0.6
    },
    {
      "epoch": 2,
      "train_loss": 0.05586995625047274,
      "clip_acc": 0.18181818181818182,
      "clip_f1": 0.18181818181818182,
      "clip_auc": 0.14468864468864467,
      "video_acc": 0.3076923076923077,
      "video_f1": 0.3076923076923077,
      "video_auc": 0.175
    },
    {
      "epoch": 3,
      "train_loss": 0.045718900789256375,
      "clip_acc": 0.41818181818181815,
      "clip_f1": 0.5789473684210527,
      "clip_auc": 0.16666666666666666,
      "video_acc": 0.15384615384615385,
      "video_f1": 0.26666666666666666,
      "video_auc": 0.125
    },
    {
      "epoch": 4,
      "train_loss": 0.04076908125231663,
      "clip_acc": 0.4,
      "clip_f1": 0.5352112676056338,
      "clip_auc": 0.23443223443223443,
      "video_acc": 0.15384615384615385,
      "video_f1": 0.26666666666666666,
      "video_auc": 0.15
    },
    {
      "epoch": 5,
      "train_loss": 0.03987267062628782,
      "clip_acc": 0.43636363636363634,
      "clip_f1": 0.5974025974025974,
      "clip_auc": 0.09157509157509156,
      "video_acc": 0.23076923076923078,
      "video_f1": 0.2857142857142857,
      "video_auc": 0.075
    },
    {
      "epoch": 6,
      "train_loss": 0.04028759761563232,
      "clip_acc": 0.16363636363636364,
      "clip_f1": 0.28125,
      "clip_auc": 0.010989010989010986,
      "video_acc": 0.15384615384615385,
      "video_f1": 0.26666666666666666,
      "video_auc": 0.05
    },
    {
      "epoch": 7,
      "train_loss": 0.031541995173420316,
      "clip_acc": 0.14545454545454545,
      "clip_f1": 0.2033898305084746,
      "clip_auc": 0.03479853479853479,
      "video_acc": 0.07692307692307693,
      "video_f1": 0.14285714285714285,
      "video_auc": 0.05
    },
    {
      "epoch": 8,
      "train_loss": 0.03269106528211024,
      "clip_acc": 0.09090909090909091,
      "clip_f1": 0.038461538461538464,
      "clip_auc": 0.07875457875457875,
      "video_acc": 0.3076923076923077,
      "video_f1": 0.3076923076923077,
      "video_auc": 0.15000000000000002
    },
    {
      "epoch": 9,
      "train_loss": 0.03757413303459524,
      "clip_acc": 0.36363636363636365,
      "clip_f1": 0.5333333333333333,
      "clip_auc": 0.018315018315018312,
      "video_acc": 0.23076923076923078,
      "video_f1": 0.375,
      "video_auc": 0.12499999999999999
    },
    {
      "epoch": 10,
      "train_loss": 0.03557571260288598,
      "clip_acc": 0.09090909090909091,
      "clip_f1": 0.13793103448275862,
      "clip_auc": 0.01831501831501831,
      "video_acc": 0.15384615384615385,
      "video_f1": 0.26666666666666666,
      "video_auc": 0.024999999999999994
    }
  ],
  "config": {
    "train": {
      "epochs": 10,
      "batch_size": 8,
      "lr": 0.0001,
      "wd": 0.0001,
      "k_frames": 8,
      "seed": 42,
      "num_workers": 2,
      "cpu": false,
      "log_level": "INFO"
    },
    "eval": {
      "agg": "max",
      "clip_threshold": 0.5,
      "video_threshold": 0.4,
      "ratio_threshold": 0.6
    },
    "model": {
      "name": "temporal_avg_resnet18",
      "pretrained": true
    }
  }
}